Angular2ZhongwenWendang/README.md
Angular2ZhongwenWendang/__init__.py
Angular2ZhongwenWendang/__main__.py
Angular2ZhongwenWendang/file.epub
Angular2ZhongwenWendang/index.html
Angular2ZhongwenWendang/css/__init__.py
Angular2ZhongwenWendang/css/annotations.css
Angular2ZhongwenWendang/css/main.css
Angular2ZhongwenWendang/css/normalize.css
Angular2ZhongwenWendang/css/popup.css
Angular2ZhongwenWendang/font/__init__.py
Angular2ZhongwenWendang/font/fontello.eot
Angular2ZhongwenWendang/font/fontello.svg
Angular2ZhongwenWendang/font/fontello.ttf
Angular2ZhongwenWendang/font/fontello.woff
Angular2ZhongwenWendang/img/__init__.py
Angular2ZhongwenWendang/img/annotator-glyph-sprite.png
Angular2ZhongwenWendang/img/annotator-icon-sprite.png
Angular2ZhongwenWendang/img/apple-touch-icon.png
Angular2ZhongwenWendang/img/cancelfullscreen.png
Angular2ZhongwenWendang/img/close.png
Angular2ZhongwenWendang/img/fullscreen.png
Angular2ZhongwenWendang/img/loader.gif
Angular2ZhongwenWendang/img/menu-icon.png
Angular2ZhongwenWendang/img/save.png
Angular2ZhongwenWendang/img/saved.png
Angular2ZhongwenWendang/img/settings-s.png
Angular2ZhongwenWendang/img/settings.png
Angular2ZhongwenWendang/img/star.png
Angular2ZhongwenWendang/js/__init__.py
Angular2ZhongwenWendang/js/epub.js
Angular2ZhongwenWendang/js/epub.min.js
Angular2ZhongwenWendang/js/epub.min.map
Angular2ZhongwenWendang/js/hooks.min.js
Angular2ZhongwenWendang/js/hooks.min.map
Angular2ZhongwenWendang/js/reader.js
Angular2ZhongwenWendang/js/reader.js.map
Angular2ZhongwenWendang/js/reader.min.js
Angular2ZhongwenWendang/js/reader.min.map
Angular2ZhongwenWendang/js/hooks/__init__.py
Angular2ZhongwenWendang/js/hooks/extensions/__init__.py
Angular2ZhongwenWendang/js/hooks/extensions/highlight.js
Angular2ZhongwenWendang/js/libs/__init__.py
Angular2ZhongwenWendang/js/libs/jquery.min.js
Angular2ZhongwenWendang/js/libs/localforage.min.js
Angular2ZhongwenWendang/js/libs/screenfull.js
Angular2ZhongwenWendang/js/libs/screenfull.min.js
angular_2_zhongwen_wendang-2024.2.29.0.dist-info/METADATA
angular_2_zhongwen_wendang-2024.2.29.0.dist-info/WHEEL
angular_2_zhongwen_wendang-2024.2.29.0.dist-info/entry_points.txt
angular_2_zhongwen_wendang-2024.2.29.0.dist-info/top_level.txt
angular_2_zhongwen_wendang-2024.2.29.0.dist-info/RECORD
